alignak/__init__.py
alignak/acknowledge.py
alignak/action.py
alignak/alignakobject.py
alignak/autoslots.py
alignak/basemodule.py
alignak/borg.py
alignak/brok.py
alignak/check.py
alignak/commandcall.py
alignak/comment.py
alignak/complexexpression.py
alignak/contactdowntime.py
alignak/daemon.py
alignak/daterange.py
alignak/dependencynode.py
alignak/dispatcher.py
alignak/downtime.py
alignak/eventhandler.py
alignak/external_command.py
alignak/graph.py
alignak/log.py
alignak/macroresolver.py
alignak/message.py
alignak/modulesmanager.py
alignak/monitor.py
alignak/notification.py
alignak/property.py
alignak/satellite.py
alignak/scheduler.py
alignak/stats.py
alignak/util.py
alignak/version.py
alignak/worker.py
alignak/bin/__init__.py
alignak/bin/alignak_arbiter.py
alignak/bin/alignak_broker.py
alignak/bin/alignak_environment.py
alignak/bin/alignak_poller.py
alignak/bin/alignak_reactionner.py
alignak/bin/alignak_receiver.py
alignak/bin/alignak_scheduler.py
alignak/daemons/__init__.py
alignak/daemons/arbiterdaemon.py
alignak/daemons/brokerdaemon.py
alignak/daemons/pollerdaemon.py
alignak/daemons/reactionnerdaemon.py
alignak/daemons/receiverdaemon.py
alignak/daemons/schedulerdaemon.py
alignak/http/__init__.py
alignak/http/arbiter_interface.py
alignak/http/broker_interface.py
alignak/http/cherrypy_extend.py
alignak/http/client.py
alignak/http/daemon.py
alignak/http/generic_interface.py
alignak/http/scheduler_interface.py
alignak/misc/__init__.py
alignak/misc/carboniface.py
alignak/misc/common.py
alignak/misc/custom_module.py
alignak/misc/perfdata.py
alignak/misc/serialization.py
alignak/modules/__init__.py
alignak/modules/inner_metrics.py
alignak/modules/inner_retention.py
alignak/objects/__init__.py
alignak/objects/arbiterlink.py
alignak/objects/brokerlink.py
alignak/objects/businessimpactmodulation.py
alignak/objects/checkmodulation.py
alignak/objects/command.py
alignak/objects/commandcallitem.py
alignak/objects/config.py
alignak/objects/contact.py
alignak-2.1.5.dist-info/LICENSE
alignak-2.1.5.dist-info/METADATA
alignak-2.1.5.dist-info/WHEEL
alignak-2.1.5.dist-info/dependency_links.txt
alignak-2.1.5.dist-info/entry_points.txt
alignak-2.1.5.dist-info/top_level.txt
alignak-2.1.5.dist-info/RECORD
