Metadata-Version: 2.1
Name: alignak
Version: 2.1.5
Summary: Alignak is a monitoring framework compatible with Nagios configuration and plugins
Home-page: https://github.com/alignak-monitoring/alignak
Author: Alignak Team
Author-email: contact@alignak.net
License: GNU Affero General Public License
Download-URL: https://github.com/Alignak-monitoring/alignak/archive/master.tar.gz
Project-URL: Presentation, http://alignak.net
Project-URL: Documentation, http://docs.alignak.net/en/latest/
Project-URL: Source, https://github.com/alignak-monitoring/alignak/
Project-URL: Tracker, https://github.com/alignak-monitoring/alignak/issues
Project-URL: Contributions, https://github.com/alignak-monitoring-contrib/
Keywords: python monitoring nagios shinken
Platform: any
Classifier: Development Status :: 5 - Production/Stable
Classifier: Environment :: Console
Classifier: Intended Audience :: Customer Service
Classifier: Intended Audience :: Information Technology
Classifier: Intended Audience :: System Administrators
Classifier: License :: OSI Approved :: GNU Affero General Public License v3
Classifier: Natural Language :: English
Classifier: Operating System :: POSIX
Classifier: Operating System :: POSIX :: Linux
Classifier: Operating System :: POSIX :: BSD :: FreeBSD
Classifier: Topic :: System
Classifier: Topic :: System :: Monitoring
Classifier: Topic :: System :: Networking :: Monitoring
Classifier: Programming Language :: Python
Classifier: Programming Language :: Python :: 2
Classifier: Programming Language :: Python :: 2.7
Classifier: Programming Language :: Python :: 3
Classifier: Programming Language :: Python :: 3.5
Classifier: Programming Language :: Python :: 3.6
Requires-Dist: future
Requires-Dist: six
Requires-Dist: CherryPy (==15.0.0)
Requires-Dist: requests (==2.20.0)
Requires-Dist: termcolor (==1.1.0)
Requires-Dist: setproctitle (==1.1.10)
Requires-Dist: ujson (==1.35)
Requires-Dist: numpy (==1.14.3)
Requires-Dist: docopt
Requires-Dist: psutil (<=5.4.5,>=5.4.3)
Requires-Dist: importlib ; python_version == "2.7"
Requires-Dist: configparser ; python_version == "2.7"
